daft/.ruff.toml
daft/__init__.py
daft/analytics.py
daft/api_annotations.py
daft/arrow_utils.py
daft/catalog/__glue.py
daft/catalog/__iceberg.py
daft/catalog/__init__.py
daft/catalog/__memory.py
daft/catalog/__rust.py
daft/catalog/__s3tables.py
daft/catalog/__unity.py
daft/catalog/pyiceberg.py
daft/catalog/python_catalog.py
daft/catalog/unity.py
daft/cli.py
daft/context.py
daft/convert.py
daft/daft.abi3.so
daft/daft/__init__.pyi
daft/daft/dashboard.pyi
daft/daft/testing.pyi
daft/dashboard/__init__.py
daft/dataframe/__init__.py
daft/dataframe/dataframe.py
daft/dataframe/display.py
daft/dataframe/lance_data_sink.py
daft/dataframe/preview.py
daft/dataframe/to_torch.py
daft/datatype.py
daft/delta_lake/__init__.py
daft/delta_lake/delta_lake_scan.py
daft/delta_lake/delta_lake_write.py
daft/dependencies.py
daft/errors.py
daft/exceptions.py
daft/execution/__init__.py
daft/execution/actor_pool_udf.py
daft/execution/execution_step.py
daft/execution/native_executor.py
daft/execution/physical_plan.py
daft/execution/rust_physical_plan_shim.py
daft/execution/shuffles/flight_shuffle/flight_shuffle.py
daft/execution/shuffles/pre_shuffle_merge.py
daft/expressions/__init__.py
daft/expressions/expressions.py
daft/expressions/testing.py
daft/expressions/visitor.py
daft/filesystem.py
daft/functions/__init__.py
daft/functions/functions.py
daft/functions/llm_generate.py
daft/hudi/__init__.py
daft/hudi/hudi_scan.py
daft/hudi/pyhudi/__init__.py
daft/hudi/pyhudi/filegroup.py
daft/hudi/pyhudi/table.py
daft/hudi/pyhudi/timeline.py
daft/hudi/pyhudi/utils.py
daft/iceberg/__init__.py
daft/iceberg/iceberg_scan.py
daft/iceberg/iceberg_write.py
daft/iceberg/schema_field_id_mapping_visitor.py
daft/internal/__init__.py
daft/internal/gpu.py
daft/io/__init__.py
daft/io/__shim.py
daft/io/_csv.py
daft/io/_deltalake.py
daft/io/_generator.py
daft/io/_hudi.py
daft/io/_iceberg.py
daft/io/_json.py
daft/io/_lance.py
daft/io/_parquet.py
daft/io/_range.py
daft/io/_sql.py
daft/io/_warc.py
daft/io/aws_config.py
getdaft-0.4.18.dist-info/METADATA
getdaft-0.4.18.dist-info/WHEEL
getdaft-0.4.18.dist-info/entry_points.txt
getdaft-0.4.18.dist-info/licenses/LICENSE
getdaft-0.4.18.dist-info/RECORD
